lprp_detr/__init__.py
lprp_detr/d2/README.md
lprp_detr/d2/__init__.py
lprp_detr/d2/configs/detr_256_6_6_torchvision.yaml
lprp_detr/d2/configs/detr_segm_256_6_6_torchvision.yaml
lprp_detr/d2/converter.py
lprp_detr/d2/detr/__init__.py
lprp_detr/d2/detr/config.py
lprp_detr/d2/detr/dataset_mapper.py
lprp_detr/d2/detr/detr.py
lprp_detr/d2/train_net.py
lprp_detr/datasets/__init__.py
lprp_detr/datasets/coco.py
lprp_detr/datasets/coco_eval.py
lprp_detr/datasets/coco_panoptic.py
lprp_detr/datasets/panoptic_eval.py
lprp_detr/datasets/transforms.py
lprp_detr/detr_attention.ipynb
lprp_detr/engine.py
lprp_detr/external_panopticapi/__init__.py
lprp_detr/external_panopticapi/combine_semantic_and_instance_predictions.py
lprp_detr/external_panopticapi/evaluation.py
lprp_detr/external_panopticapi/utils.py
lprp_detr/finetune_detr.ipynb
lprp_detr/hubconf.py
lprp_detr/main.py
lprp_detr/models/__init__.py
lprp_detr/models/backbone.py
lprp_detr/models/detr.py
lprp_detr/models/matcher.py
lprp_detr/models/position_encoding.py
lprp_detr/models/segmentation.py
lprp_detr/models/transformer.py
lprp_detr/run_with_submitit.py
lprp_detr/test_all.py
lprp_detr/util/__init__.py
lprp_detr/util/box_ops.py
lprp_detr/util/misc.py
lprp_detr/util/plot_utils.py
lprp_detr-0.1.3.dist-info/LICENSE
lprp_detr-0.1.3.dist-info/METADATA
lprp_detr-0.1.3.dist-info/WHEEL
lprp_detr-0.1.3.dist-info/RECORD
