Metadata-Version: 2.1
Name: lprp-detr
Version: 0.1.3
Summary: 
Author: Example Person
Author-email: person@example.com
Requires-Python: >=3.8,<3.11
Classifier: Programming Language :: Python :: 3
Classifier: Programming Language :: Python :: 3.8
Classifier: Programming Language :: Python :: 3.9
Classifier: Programming Language :: Python :: 3.10
Requires-Dist: Cython (>=0.29.32,<0.30.0)
Requires-Dist: numpy (>=1.23.2,<2.0.0)
Requires-Dist: pycocotools (>=2.0.4,<3.0.0)
Requires-Dist: scipy (>=1.9.1,<2.0.0)
Requires-Dist: submitit (>=1.4.5,<2.0.0)
Requires-Dist: torch (>=1.13.1+cu116,<2.0.0)
Requires-Dist: torchvision (>=0.14.1+cu116,<0.15.0)
